LICENSE
MANIFEST.in
README
gevent_worker.py
setup.py
gevent_worker.egg-info/PKG-INFO
gevent_worker.egg-info/SOURCES.txt
gevent_worker.egg-info/dependency_links.txt
gevent_worker.egg-info/not-zip-safe
gevent_worker.egg-info/requires.txt
gevent_worker.egg-info/top_level.txt