Metadata-Version: 1.0
Name: gevent-worker
Version: 0.0.1
Summary: gevent worker libs.
Home-page: https://github.com/endsh/gevent-worker
Author: Linshao
Author-email: 438985635@qq.com
License: UNKNOWN
Platform: any
